marvellous.py
app/__init__.py
app/__main__.py
app/application.py
MIDupFileRemove-0.0.3.dist-info/LICENSE
MIDupFileRemove-0.0.3.dist-info/METADATA
MIDupFileRemove-0.0.3.dist-info/WHEEL
MIDupFileRemove-0.0.3.dist-info/entry_points.txt
MIDupFileRemove-0.0.3.dist-info/top_level.txt
MIDupFileRemove-0.0.3.dist-info/RECORD
