Metadata-Version: 2.1
Name: MIDupFileRemove
Version: 0.0.3
Summary: Duplicate file removal packages
Home-page: UNKNOWN
Author: Vijay Thorat
Author-email: vijaythorat0804@gmail.com
License: MIT License
Platform: UNKNOWN
Classifier: Programming Language :: Python :: 3.8
Classifier: Operating System :: OS Independent
Requires-Python: >=3.7
Requires-Dist: Click (==7.0)
Requires-Dist: psutil (==5.9.4)
Requires-Dist: setuptools (==45.2.0)
